{
  "idProcesos": [],
  "numero": 186,
  "cc": 24134505,
  "llaveProceso": "25175408900220170041200",
  "category": "Reintegra",
  "tipoProceso": "SINGULAR",
  "deudor": {
    "tel": {},
    "primerNombre": "",
    "segundoNombre": "CELY",
    "primerApellido": "MARGOTH",
    "segundoApellido": "ROJAS VELANDIA",
    "cedula": 24134505,
    "direccion": "CALLE 29 A # 2 - 76 APTO 304 CHIA"
  },
  "demanda": {
    "capitalAdeudado": 13319.13,
    "departamento": "CUNDINAMARCA",
    "entregaGarantiasAbogado": "2017-08-11T00:00:00.000Z",
    "tipoProceso": "SINGULAR",
    "mandamientoPago": "2017-09-19T00:00:00.000Z",
    "etapaProcesal": "EJECUCIÓN",
    "fechaPresentacion": "2017-08-15T00:00:00.000Z",
    "municipio": "CHIA",
    "obligacion": [1680097051],
    "radicado": "2017 - 00412",
    "vencimientoPagare": [
      "2021-01-29T00:00:00.000Z"
    ],
    "expediente": "25175408900220170041200",
    "juzgados": []
  }
}
