{
  "category": "Reintegra",
  "deudor": {
    "tel": {
      "fijo": 7836655,
      "celular": 3118163887
    },
    "primerNombre": "ORLANDO",
    "segundoNombre": "ENRIQUE",
    "primerApellido": "NOVOA",
    "segundoApellido": "BARRETO",
    "cedula": 80733467,
    "direccion": "CARRERA 88 A No  67 - 44",
    "email": "orlandonovoa9@gmail.com"
  },
  "numero": 396,
  "tipoProceso": "SINGULAR",
  "idProceso": 112730580,
  "llaveProceso": "11001400306420170162300",
  "categoryTag": 2,
  "demanda": {
    "departamento": "CUNDINAMARCA",
    "juzgados": [
      {
        "id": 16,
        "tipo": "JUZGADO 016 CIVIL MUNICIPAL DE EJECUCIÓN DE SENTENCIAS DE BOGOTÁ",
        "url": "https://www.ramajudicial.gov.co/web/juzgado-16-de-ejecucion-civil-municipal-de-bogota"
      }
    ],
    "capitalAdeudado": 24000,
    "entregaGarantiasAbogado": "2017-11-15T00:00:00.000Z",
    "etapaProcesal": "EJECUCIÓN",
    "fechaPresentacion": "2017-11-21T00:00:00.000Z",
    "municipio": "BOGOTA",
    "obligacion": {
      "0": 10000090724,
      "1": "N/A"
    },
    "radicado": "2017 - 01623",
    "vencimientoPagare": [
      "2019-06-08T00:00:00.000Z"
    ],
    "expediente": "11001400306420170162300"
  }
}
