{
  "idProcesos": [17724160],
  "numero": 436,
  "cc": 79145374,
  "llaveProceso": "11001400306320180075600",
  "category": "Terminados",
  "tipoProceso": "SINGULAR",
  "deudor": {
    "tel": {},
    "primerNombre": "JUAN",
    "segundoNombre": "CAMILO",
    "primerApellido": "BAQUERO",
    "segundoApellido": "BUTTNER",
    "cedula": 79145374,
    "direccion": "TRANSVERSAL 2A No 67-71",
    "email": "jcbaquerob@gmail.com"
  },
  "demanda": {
    "capitalAdeudado": null,
    "departamento": "CUNDINAMARCA",
    "entregaGarantiasAbogado": "2018-05-23T00:00:00.000Z",
    "tipoProceso": "SINGULAR",
    "mandamientoPago": null,
    "etapaProcesal": "ADMISION",
    "fechaPresentacion": "2018-05-31T00:00:00.000Z",
    "municipio": "BOGOTA",
    "obligacion": [
      5491585909873,
      "AUDIOPRESTAMO"
    ],
    "radicado": "2018 - 00756",
    "vencimientoPagare": [
      "2015-01-01T00:00:00.000Z"
    ],
    "expediente": "11001400306320180075600",
    "juzgados": [
      {
        "id": 63,
        "tipo": "JUZGADO 063 CIVIL MUNICIPAL DE BOGOTÁ",
        "url": "https://www.ramajudicial.gov.co/web/juzgado-63-civil-municipal-de-bogota"
      }
    ]
  }
}
