{
  "llaveProceso": "11001400306420170113800",
  "category": "Terminados",
  "numero": 54,
  "tipoProceso": "HIPOTECARIO",
  "deudor": {
    "cedula": 38261511,
    "direccion": "carrera 87d no. 48-03 sur//diagonal 49 no. 85-79 sur torre 10 apartamento 2",
    "email": "olgagallego63@hotmail.com",
    "tel": {
      "fijo": null,
      "celular": 3138615288
    },
    "primerNombre": "olga",
    "primerApellido": "gallego",
    "segundoApellido": null,
    "segundoNombre": null
  },
  "cc": 38261511,
  "idProcesos": [17941680],
  "demanda": {
    "tipoProceso": "SINGULAR",
    "expediente": "11001400306420170113800",
    "capitalAdeudado": 18400665,
    "entregaGarantiasAbogado": "2017-06-12T00:00:00.000Z",
    "etapaProcesal": "NOTIFICACION",
    "fechaPresentacion": "2017-06-21T00:00:00.000Z",
    "juzgados": [
      {
        "id": 64,
        "tipo": "JUZGADO 064 CIVIL MUNICIPAL DE BOGOTÁ",
        "url": "https://www.ramajudicial.gov.co/web/juzgado-064-civil-municipal-de-bogota"
      }
    ],
    "municipio": "BOGOTA",
    "mandamientoPago": "2017-08-25T00:00:00.000Z",
    "obligacion": [320095437],
    "radicado": "2017 - 01138",
    "vencimientoPagare": [
      "2022-04-02T00:00:00.000Z"
    ],
    "departamento": "CUNDINAMARCA"
  }
}
