{
  "_id": "64e8790ba35a5c13a887bc31",
  "demanda": {
    "departamento": {
      "idCatalogoDetalle": 13,
      "idCatalogoDetallePadre": 1,
      "descripcion": "CUNDINAMARCA",
      "codigo": "25"
    },
    "capitalAdeudado": 0,
    "entregagarantiasAbogado": "1970-01-01T00:00:00.000Z",
    "etapaProcesal": "15/08/2018",
    "fechaPresentacion": "1970-01-01T00:00:00.000Z",
    "municipio": "SOACHA",
    "obligacion": { "1": "", "2": "" },
    "radicado": "2018 - 00855",
    "vencimientoPagare": "1970-01-01T00:00:00.000Z",
    "expediente": "25754418900320180085500",
    "juzgados": []
  },
  "category": "Terminados",
  "categoryTag": 5,
  "deudor": {
    "tel": { "fijo": 0, "celular": 0 },
    "primerNombre": "SANDRA",
    "segundoNombre": "MILENA",
    "primerApellido": "VEGA",
    "segundoApellido": "AVILA",
    "cedula": 52725153,
    "direccion": "",
    "email": "TRANSVERSAL 2 ESTE No 32B-80 SUR "
  },
  "numero": 473,
  "llaveProceso": "25754418900320180085500",
  "tipoProceso": "HIPOTECARIO"
}
