{"idProcesos":[65640840],"numero":70,"cc":14250539,"llaveProceso":"11001400308520170108400","category":"Terminados","tipoProceso":"PRENDARIO","deudor":{"tel":{"celular":3152248920},"primerNombre":"CESAR","primerApellido":"AUGUSTO","segundoApellido":"ARIAS","cedula":14250539,"direccion":"CALLE 54 # 22 - 50","email":"ariascesaraugustoarias@gmail.com"},"demanda":{"capitalAdeudado":74069.982,"departamento":"CUNDINAMARCA","entregaGarantiasAbogado":"2017-06-12T00:00:00.000Z","tipoProceso":"SINGULAR","mandamientoPago":"2017-06-14T00:00:00.000Z","etapaProcesal":"11001400308520170108400","fechaPresentacion":null,"municipio":"BOGOTA","obligacion":{"A":12587175},"radicado":"2017 - 01084","vencimientoPagare":["2017-06-07T00:00:00.000Z"],"expediente":"11001400308520170108400","juzgados":[{"id":85,"tipo":"JUZGADO 085 CIVIL MUNICIPAL DE BOGOTÁ ","url":"https://www.ramajudicial.gov.cojuzgado-085-civil-municipal-de-bogotá-"}]}}