{"numero":87,"cc":4198210,"llaveProceso":"11001400304620170056100","idProcesos":[],"category":"Terminados","tipoProceso":"SINGULAR","deudor":{"tel":{},"primerNombre":"OMAR","primerApellido":"ESPITIA","segundoApellido":"REYES","cedula":4198210,"direccion":"CALLE 39 I # 72F - 53 SUR ","email":"omar690501@hotmail.com"},"demanda":{"capitalAdeudado":11777235,"departamento":"CUNDINAMARCA","entregaGarantiasAbogado":"2017-06-12T00:00:00.000Z","tipoProceso":"SINGULAR","mandamientoPago":"2017-07-27T00:00:00.000Z","etapaProcesal":"NOTIFICACION","fechaPresentacion":"2017-06-20T00:00:00.000Z","municipio":"BOGOTA","obligacion":{"A":2150091074},"radicado":"2017 - 00561","vencimientoPagare":null,"expediente":"11001400304620170056100","juzgados":[]}}